scrapemyst/ScrapeMyst.py
scrapemyst/__init__.py
scrapemyst-1.0.2.dist-info/LICENSE
scrapemyst-1.0.2.dist-info/METADATA
scrapemyst-1.0.2.dist-info/WHEEL
scrapemyst-1.0.2.dist-info/top_level.txt
scrapemyst-1.0.2.dist-info/RECORD
